google_maps_scraper/__init__.py
google_maps_scraper/main.py
google_maps_scraper/test.py
hexaa_business_scraper-0.4.dist-info/LICENSE
hexaa_business_scraper-0.4.dist-info/METADATA
hexaa_business_scraper-0.4.dist-info/WHEEL
hexaa_business_scraper-0.4.dist-info/entry_points.txt
hexaa_business_scraper-0.4.dist-info/top_level.txt
hexaa_business_scraper-0.4.dist-info/RECORD
