Metadata-Version: 2.1
Name: hexaa_business_scraper
Version: 0.4
Summary: A Flask-based business scraper leveraging Playwright and Google Maps
Home-page: https://github.com/dilawaizkhan08/Google_Maps_Scraper
Author: Dilawaiz Khan
Author-email: dilawaizkhan08@gmail.com
License: MIT
Classifier: Development Status :: 4 - Beta
Classifier: Programming Language :: Python :: 3
Classifier: Programming Language :: Python :: 3.8
Classifier: Programming Language :: Python :: 3.9
Classifier: Programming Language :: Python :: 3.10
Classifier: Framework :: Flask
Classifier: License :: OSI Approved :: MIT License
Classifier: Operating System :: OS Independent
Requires-Python: >=3.8
License-File: LICENSE
Requires-Dist: flask
Requires-Dist: playwright
Requires-Dist: pandas
Requires-Dist: flask-cors
